Metadata-Version: 2.1
Name: aspose-tasks
Version: 26.1.0
Summary: Aspose.Tasks for Python via .NET is a native library that enables the developers to add MS-Project files processing capabilities to their applications
Home-page: https://products.aspose.com/tasks/python-net
Author: Aspose
License: Other/Proprietary License
Keywords: project,msproject,timeline,primavera,oracle,openproj,MPP,MPX,MPT,XER,import,export,convert,XML,BMP,PNG,PDF,XPS,GPG,GPEG,SVG,HTML,TIFF,XAML,CSV,TXT,XLSX,mpp-to-image,mpp-to-xml,mpp-to-bmp,mpp-to-png,mpp-to-jpg,mpp-to-jpeg,mpp-to-svg,mpp-to-tiff,mpp-to-pdf,mpp-to-xps,mpp-to-xaml,mpp-to-html,mpp-to-csv,mpp-to-text,mpp-to-txt,mpp-to-xls,mpp-to-xlsx
Platform: win_amd64
Classifier: Operating System :: Microsoft :: Windows
Classifier: Operating System :: POSIX :: Linux
Classifier: Operating System :: Unix
Classifier: Operating System :: MacOS
Classifier: License :: Other/Proprietary License
Classifier: Programming Language :: Python :: 3
Classifier: Programming Language :: Python :: 3 :: Only
Classifier: Programming Language :: Python :: 3.5
Classifier: Programming Language :: Python :: 3.6
Classifier: Programming Language :: Python :: 3.7
Classifier: Programming Language :: Python :: 3.8
Classifier: Programming Language :: Python :: 3.9
Classifier: Programming Language :: Python :: 3.10
Classifier: Programming Language :: Python :: 3.11
Classifier: Programming Language :: Python :: 3.12
Classifier: Programming Language :: Python :: 3.13
Classifier: Topic :: Software Development :: Libraries
Classifier: Topic :: Office/Business
Classifier: Topic :: Office/Business :: Scheduling
Requires-Python: >=3.5,<3.14
